README.rst
setup.py
mec2/__init__.py
mec2/main.py
mec2/mec2.py
mec2.egg-info/PKG-INFO
mec2.egg-info/SOURCES.txt
mec2.egg-info/dependency_links.txt
mec2.egg-info/entry_points.txt
mec2.egg-info/requires.txt
mec2.egg-info/top_level.txt